bin/__init__.py
bin/cli.py
src/__init__.py
src/core/__init__.py
src/core/base_usecase.py
src/core/configuration.py
src/core/documentation.py
src/core/entity.py
src/core/project.py
src/core/search_pattern.py
src/core/code/__init__.py
src/core/code/dispatcher.py
src/core/code/language.py
src/core/code/languages/__init__.py
src/core/code/languages/go.py
src/core/code/languages/java.py
src/core/code/languages/javascript.py
src/core/code/languages/python.py
src/core/code/languages/ruby.py
src/core/code/languages/typescript.py
src/helpers/__init__.py
src/helpers/bipartite_matching.py
src/helpers/comparison.py
src/helpers/comparison_legacy.py
src/helpers/file_system.py
src/helpers/json.py
src/helpers/logger.py
src/use_cases/partial_lists.py
src/use_cases/pattern_search.py
src/use_cases/spellcheck.py
src/use_cases/unused_modules.py
ducku-1.2.0.dist-info/METADATA
ducku-1.2.0.dist-info/WHEEL
ducku-1.2.0.dist-info/entry_points.txt
ducku-1.2.0.dist-info/licenses/LICENSE
ducku-1.2.0.dist-info/RECORD
