Metadata-Version: 2.4
Name: ducku
Version: 1.2.0
Summary: Documentation analysis and code quality tool for multi-language projects
Project-URL: Homepage, https://github.com/duckuio/ducku_cli
Project-URL: Repository, https://github.com/duckuio/ducku_cli
Project-URL: Issues, https://github.com/duckuio/ducku_cli/issues
Project-URL: Documentation, https://github.com/duckuio/ducku_cli#readme
Author: Roman Krivtsov
Maintainer: Roman Krivtsov
License: Ducku Source Available License (DSAL)
License-File: LICENSE
Keywords: code-analysis,dead-code,documentation,linting,static-analysis
Classifier: Development Status :: 4 - Beta
Classifier: Environment :: Console
Classifier: Intended Audience :: Developers
Classifier: License :: OSI Approved :: MIT License
Classifier: Operating System :: OS Independent
Classifier: Programming Language :: Python :: 3
Classifier: Programming Language :: Python :: 3.10
Classifier: Topic :: Documentation
Classifier: Topic :: Software Development :: Code Generators
Classifier: Topic :: Software Development :: Documentation
Classifier: Topic :: Software Development :: Quality Assurance
Classifier: Topic :: Utilities
Requires-Python: >=3.10
Requires-Dist: anytree>=2.13.0
Requires-Dist: codespell>=2.4.1
Requires-Dist: jsonschema>=4.25.1
Requires-Dist: markdown-it-py>=4.0.0
Requires-Dist: marko>=2.2.0
Requires-Dist: pydantic>=2.12.5
Requires-Dist: pyyaml
Requires-Dist: rapidfuzz>=3.14.0
Requires-Dist: tree-sitter-go
Requires-Dist: tree-sitter-java
Requires-Dist: tree-sitter-javascript
Requires-Dist: tree-sitter-php
Requires-Dist: tree-sitter-python
Requires-Dist: tree-sitter-ruby
Requires-Dist: tree-sitter-rust
Requires-Dist: tree-sitter-typescript
Requires-Dist: tree-sitter>=0.23.0
